{
  "updated": "2026-06-18 10:21 UTC",
  "count": 25,
  "events": [
    {
      "id": "fc81c6f4797a",
      "category": "exhibition",
      "title": "Julio Le Parc",
      "subtitle": "",
      "type": "Exhibition",
      "venue": "Tate Modern",
      "area": "London",
      "date_text": "11 June 2026 - 3 May 2027",
      "start": "2026-06-11",
      "end": "2027-05-03",
      "price": "£15",
      "url": "https://www.tate.org.uk/whats-on/tate-modern/julio-le-parc",
      "source": "Tate"
    },
    {
      "id": "4e59ff02e0b5",
      "category": "exhibition",
      "title": "Frida: The Making of an Icon",
      "subtitle": "",
      "type": "Exhibition",
      "venue": "Tate Modern",
      "area": "London",
      "date_text": "25 June 2026 - 3 January 2027",
      "start": "2026-06-25",
      "end": "2027-01-03",
      "price": "£25",
      "url": "https://www.tate.org.uk/whats-on/tate-modern/frida-kahlo-the-making-of-an-icon",
      "source": "Tate"
    },
    {
      "id": "379c4facc4bd",
      "category": "exhibition",
      "title": "Waldmüller: Landscapes",
      "subtitle": "",
      "type": "Exhibition",
      "venue": "National Gallery",
      "area": "London",
      "date_text": "2 July - 20 September 2026",
      "start": "2026-07-02",
      "end": "2026-09-20",
      "price": "Free",
      "url": "https://www.nationalgallery.org.uk/exhibitions/waldmüller-landscapes",
      "source": "National Gallery"
    },
    {
      "id": "65d0bf8f8a3e",
      "category": "exhibition",
      "title": "Ana Mendieta",
      "subtitle": "",
      "type": "Exhibition",
      "venue": "Tate Modern",
      "area": "London",
      "date_text": "15 July 2026 - 17 Jan 2027",
      "start": "2026-07-15",
      "end": "2027-01-17",
      "price": "£18",
      "url": "https://www.tate.org.uk/whats-on/tate-modern/ana-mendieta",
      "source": "Tate"
    },
    {
      "id": "e2d7a269148c",
      "category": "exhibition",
      "title": "Renoir and Love",
      "subtitle": "",
      "type": "Exhibition",
      "venue": "National Gallery",
      "area": "London",
      "date_text": "3 October 2026 - 31 January 2027",
      "start": "2026-10-03",
      "end": "2027-01-31",
      "price": "£",
      "url": "https://www.nationalgallery.org.uk/exhibitions/renoir-and-love",
      "source": "National Gallery"
    },
    {
      "id": "e0292619ca32",
      "category": "exhibition",
      "title": "The 90s: Art and Fashion",
      "subtitle": "",
      "type": "Exhibition",
      "venue": "Tate Britain",
      "area": "London",
      "date_text": "8 October 2026 - 14 February 2027",
      "start": "2026-10-08",
      "end": "2027-02-14",
      "price": "£22",
      "url": "https://www.tate.org.uk/whats-on/tate-britain/the-90s",
      "source": "Tate"
    },
    {
      "id": "df48eed5c7ec",
      "category": "exhibition",
      "title": "Light and Magic",
      "subtitle": "",
      "type": "Exhibition",
      "venue": "Tate Modern",
      "area": "London",
      "date_text": "14 October 2026 - 21 February 2027",
      "start": "2026-10-14",
      "end": "2027-02-21",
      "price": "Free",
      "url": "https://www.tate.org.uk/whats-on/tate-modern/light-and-magic",
      "source": "Tate"
    },
    {
      "id": "494decde5b71",
      "category": "exhibition",
      "title": "Yinka Shonibare and Thomas Gainsborough: A Conversation",
      "subtitle": "",
      "type": "Exhibition",
      "venue": "National Gallery",
      "area": "London",
      "date_text": "15 October 2026 - 7 February 2027",
      "start": "2026-10-15",
      "end": "2027-02-07",
      "price": "Free",
      "url": "https://www.nationalgallery.org.uk/exhibitions/yinka-shonibare-and-thomas-gainsborough-a-conversation",
      "source": "National Gallery"
    },
    {
      "id": "7e5a2bb736a6",
      "category": "exhibition",
      "title": "Vanessa Bell & Duncan Grant",
      "subtitle": "",
      "type": "Exhibition",
      "venue": "Tate Britain",
      "area": "London",
      "date_text": "12 November 2026 - 11 April 2027",
      "start": "2026-11-12",
      "end": "2027-04-11",
      "price": "Free",
      "url": "https://www.tate.org.uk/whats-on/tate-britain/vanessa-bell-and-duncan-grant",
      "source": "Tate"
    },
    {
      "id": "64d336ab45a4",
      "category": "exhibition",
      "title": "Van Eyck: The Portraits",
      "subtitle": "",
      "type": "Exhibition",
      "venue": "National Gallery",
      "area": "London",
      "date_text": "21 November 2026 - 11 April 2027",
      "start": "2026-11-21",
      "end": "2027-04-11",
      "price": "£",
      "url": "https://www.nationalgallery.org.uk/exhibitions/van-eyck-the-portraits",
      "source": "National Gallery"
    },
    {
      "id": "d96381e833ad",
      "category": "exhibition",
      "title": "Monet: Painting Time",
      "subtitle": "",
      "type": "Exhibition",
      "venue": "Tate Modern",
      "area": "London",
      "date_text": "25 February - 27 June 2027",
      "start": "2027-02-25",
      "end": "2027-06-27",
      "price": "Free",
      "url": "https://www.tate.org.uk/whats-on/tate-modern/monet",
      "source": "Tate"
    },
    {
      "id": "51dc0cac02e7",
      "category": "exhibition",
      "title": "Catharina van Hemessen: Signature Works",
      "subtitle": "",
      "type": "Exhibition",
      "venue": "National Gallery",
      "area": "London",
      "date_text": "4 March - 30 May 2027",
      "start": "2027-03-04",
      "end": "2027-05-30",
      "price": "Free",
      "url": "https://www.nationalgallery.org.uk/exhibitions/catharina-van-hemessen",
      "source": "National Gallery"
    },
    {
      "id": "da642cf32d2a",
      "category": "exhibition",
      "title": "German Expressionism Modern Painting 1900-1918",
      "subtitle": "",
      "type": "Exhibition",
      "venue": "National Gallery",
      "area": "London",
      "date_text": "20 March 2027 - 1 August 2027",
      "start": "2027-03-20",
      "end": "2027-08-01",
      "price": "£",
      "url": "https://www.nationalgallery.org.uk/exhibitions/german-expressionism-modern-painting-1900-1918",
      "source": "National Gallery"
    },
    {
      "id": "75de384906b5",
      "category": "exhibition",
      "title": "Sonia Boyce",
      "subtitle": "",
      "type": "Exhibition",
      "venue": "Tate Britain",
      "area": "London",
      "date_text": "24 March - 22 August 2027",
      "start": "2027-03-24",
      "end": "2027-08-22",
      "price": "Free",
      "url": "https://www.tate.org.uk/whats-on/tate-britain/sonia-boyce",
      "source": "Tate"
    },
    {
      "id": "525e9624e9ec",
      "category": "exhibition",
      "title": "Ink",
      "subtitle": "",
      "type": "Exhibition",
      "venue": "Tate Modern",
      "area": "London",
      "date_text": "22 April - 30 August 2027",
      "start": "2027-04-22",
      "end": "2027-08-30",
      "price": "Free",
      "url": "https://www.tate.org.uk/whats-on/tate-modern/ink",
      "source": "Tate"
    },
    {
      "id": "eaee1725e0f5",
      "category": "exhibition",
      "title": "Thomas Gainsborough",
      "subtitle": "",
      "type": "Exhibition",
      "venue": "Tate Britain",
      "area": "London",
      "date_text": "20 May - 10 October 2027",
      "start": "2027-05-20",
      "end": "2027-10-10",
      "price": "Free",
      "url": "https://www.tate.org.uk/whats-on/tate-britain/thomas-gainsborough",
      "source": "Tate"
    },
    {
      "id": "946dab8de9bb",
      "category": "exhibition",
      "title": "Baya",
      "subtitle": "",
      "type": "Exhibition",
      "venue": "Tate Modern",
      "area": "London",
      "date_text": "10 June - 17 October 2027",
      "start": "2027-06-10",
      "end": "2027-10-17",
      "price": "Free",
      "url": "https://www.tate.org.uk/whats-on/tate-modern/baya",
      "source": "Tate"
    },
    {
      "id": "819a099f7ec4",
      "category": "exhibition",
      "title": "Nalini Malani",
      "subtitle": "",
      "type": "Exhibition",
      "venue": "Tate Modern",
      "area": "London",
      "date_text": "1 July 2027 - 3 January 2028",
      "start": "2027-07-01",
      "end": "2028-01-03",
      "price": "Free",
      "url": "https://www.tate.org.uk/whats-on/tate-modern/nalini-malani",
      "source": "Tate"
    },
    {
      "id": "9d165f011640",
      "category": "exhibition",
      "title": "Lynda Benglis",
      "subtitle": "",
      "type": "Exhibition",
      "venue": "Tate Modern",
      "area": "London",
      "date_text": "30 September 2027 - 5 March 2028",
      "start": "2027-09-30",
      "end": "2028-03-05",
      "price": "Free",
      "url": "https://www.tate.org.uk/whats-on/tate-modern/lynda-benglis",
      "source": "Tate"
    },
    {
      "id": "2f49894c6a64",
      "category": "exhibition",
      "title": "Edvard Munch",
      "subtitle": "",
      "type": "Exhibition",
      "venue": "Tate Modern",
      "area": "London",
      "date_text": "11 November 2027 - 23 April 2028",
      "start": "2027-11-11",
      "end": "2028-04-23",
      "price": "Free",
      "url": "https://www.tate.org.uk/whats-on/tate-modern/edvard-munch",
      "source": "Tate"
    },
    {
      "id": "b1de82b38ae4",
      "category": "exhibition",
      "title": "Hurvin Anderson",
      "subtitle": "",
      "type": "Exhibition",
      "venue": "Tate Britain",
      "area": "London",
      "date_text": "Until 23 August 2026",
      "start": null,
      "end": "2026-08-23",
      "price": "£18",
      "url": "https://www.tate.org.uk/whats-on/tate-britain/hurvin-anderson",
      "source": "Tate"
    },
    {
      "id": "502d426f51f7",
      "category": "exhibition",
      "title": "Tracey Emin",
      "subtitle": "",
      "type": "Exhibition",
      "venue": "Tate Modern",
      "area": "London",
      "date_text": "Until 31 August 2026",
      "start": null,
      "end": "2026-08-31",
      "price": "£61",
      "url": "https://www.tate.org.uk/whats-on/tate-modern/tracey-emin",
      "source": "Tate"
    },
    {
      "id": "f15a207ce16b",
      "category": "exhibition",
      "title": "James McNeill Whistler",
      "subtitle": "",
      "type": "Exhibition",
      "venue": "Tate Britain",
      "area": "London",
      "date_text": "Until 27 September 2026",
      "start": null,
      "end": "2026-09-27",
      "price": "£5",
      "url": "https://www.tate.org.uk/whats-on/tate-britain/whistler",
      "source": "Tate"
    },
    {
      "id": "3076c2084e4d",
      "category": "exhibition",
      "title": "Zurbarán",
      "subtitle": "",
      "type": "Exhibition",
      "venue": "National Gallery",
      "area": "London",
      "date_text": "Until 23 August 2026",
      "start": null,
      "end": "2026-08-23",
      "price": "£",
      "url": "https://www.nationalgallery.org.uk/exhibitions/zurbaran",
      "source": "National Gallery"
    },
    {
      "id": "cad3e08232dc",
      "category": "exhibition",
      "title": "Take One Picture 2026",
      "subtitle": "",
      "type": "Exhibition",
      "venue": "National Gallery",
      "area": "London",
      "date_text": "Until 31 August 2026",
      "start": null,
      "end": "2026-08-31",
      "price": "Free",
      "url": "https://www.nationalgallery.org.uk/exhibitions/take-one-picture-2026",
      "source": "National Gallery"
    }
  ]
}